quantdl/__init__.py
quantdl/client.py
quantdl/exceptions.py
quantdl/py.typed
quantdl/types.py
quantdl/alpha/__init__.py
quantdl/alpha/core.py
quantdl/alpha/parser.py
quantdl/alpha/types.py
quantdl/alpha/validation.py
quantdl/data/__init__.py
quantdl/data/calendar_master.py
quantdl/data/security_master.py
quantdl/operators/__init__.py
quantdl/operators/arithmetic.py
quantdl/operators/cross_sectional.py
quantdl/operators/group.py
quantdl/operators/logical.py
quantdl/operators/time_series.py
quantdl/operators/vector.py
quantdl/storage/__init__.py
quantdl/storage/cache.py
quantdl/storage/s3.py
quantdl-0.2.1.dist-info/METADATA
quantdl-0.2.1.dist-info/WHEEL
quantdl-0.2.1.dist-info/licenses/LICENSE
quantdl-0.2.1.dist-info/RECORD
