Metadata-Version: 2.4
Name: quantdl
Version: 0.2.1
Summary: Financial data fetcher for alpha research with S3 backend and local caching
Project-URL: Homepage, https://github.com/dafu-zhu/quantdl-api
Project-URL: Documentation, https://github.com/dafu-zhu/quantdl-api/blob/main/docs/user-guide.md
Project-URL: Repository, https://github.com/dafu-zhu/quantdl-api
Author: QuantDL Team
License-Expression: MIT
License-File: LICENSE
Keywords: alpha,data,finance,polars,quantitative
Classifier: Development Status :: 3 - Alpha
Classifier: Intended Audience :: Developers
Classifier: Intended Audience :: Financial and Insurance Industry
Classifier: License :: OSI Approved :: MIT License
Classifier: Programming Language :: Python :: 3
Classifier: Programming Language :: Python :: 3.12
Classifier: Programming Language :: Python :: 3.13
Classifier: Topic :: Office/Business :: Financial :: Investment
Classifier: Typing :: Typed
Requires-Python: >=3.12
Requires-Dist: numpy>=1.26.0
Requires-Dist: polars>=1.0.0
Requires-Dist: scipy>=1.12.0
Provides-Extra: dev
Requires-Dist: boto3>=1.34.0; extra == 'dev'
Requires-Dist: moto[s3]>=5.0.0; extra == 'dev'
Requires-Dist: mypy>=1.10.0; extra == 'dev'
Requires-Dist: pytest-asyncio>=0.23.0; extra == 'dev'
Requires-Dist: pytest-cov>=4.0.0; extra == 'dev'
Requires-Dist: pytest>=8.0.0; extra == 'dev'
Requires-Dist: ruff>=0.4.0; extra == 'dev'
